{
  "environment": "web",
  "format": "html",
  "prefix": "https://storage.googleapis.com",
  "mainga": "UA-49880327-14",
  "updated": "2023-07-09T04:05:59Z",
  "id": "flutter-instalacao",
  "duration": 12,
  "title": "Flutter - Instalação",
  "authors": "Rodrigo Bossini",
  "summary": "Neste codelab, você fará a instalação do framework Flutter.",
  "source": "1kvCN1kfc0JtrpM4-Q5TIa0YBSKzHA960Xlc94uI2l88",
  "theme": "flutter",
  "status": [
    "published"
  ],
  "category": [
    "flutter"
  ],
  "tags": [
    "mobile"
  ],
  "feedback": "https://github.com/professorbossini/codelab-flutter-instalacao/issues",
  "url": "flutter-instalacao"
}
